requirements.txt
rsstt/__init__.py
rsstt/__main__.py
rsstt/aio_helper.py
rsstt/entrypoint.py
rsstt/env.py
rsstt/errors_collection.py
rsstt/locks.py
rsstt/log.py
rsstt/opml_template.opml
rsstt/redirect_server.py
rsstt/version.py
rsstt/command/__init__.py
rsstt/command/administration.py
rsstt/command/customization.py
rsstt/command/misc.py
rsstt/command/opml.py
rsstt/command/sub.py
rsstt/command/types.py
rsstt/command/utils.py
rsstt/command/inner/__init__.py
rsstt/command/inner/customization.py
rsstt/command/inner/sub.py
rsstt/command/inner/utils.py
rsstt/compat/__init__.py
rsstt/compat/listparser_opml_mixin.py
rsstt/compat/utils.py
rsstt/db/__init__.py
rsstt/db/config.py
rsstt/db/effective_utils.py
rsstt/db/models.py
rsstt/db/migrations_pgsql/models/0_20211117110249_init.py
rsstt/db/migrations_pgsql/models/1_20211130051128_update.py
rsstt/db/migrations_pgsql/models/2_20220306045951_update.py
rsstt/db/migrations_pgsql/models/3_20220415030554_update.py
rsstt/db/migrations_pgsql/models/4_20240425020849_display_entry_tags.py
rsstt/db/migrations_sqlite/models/0_20211117110249_init.py
rsstt/db/migrations_sqlite/models/1_20211130051128_update.py
rsstt/db/migrations_sqlite/models/2_20220306045951_update.py
rsstt/db/migrations_sqlite/models/3_20220415025716_update.py
rsstt/db/migrations_sqlite/models/4_20240425020849_display_entry_tags.py
rsstt/helpers/__init__.py
rsstt/helpers/bg/__init__.py
rsstt/helpers/bg/_common.py
rsstt/helpers/bg/_decorator.py
rsstt/helpers/bg/_helper.py
rsstt/helpers/pipeline/__init__.py
rsstt/helpers/pipeline/_exceptions.py
rsstt/helpers/pipeline/_pipeline.py
rsstt/helpers/queue/__init__.py
rsstt/helpers/queue/_common.py
rsstt/helpers/queue/_decorator.py
rsstt/helpers/queue/_helper.py
rsstt/helpers/singleton/__init__.py
rsstt/helpers/singleton/_singleton.py
rsstt/helpers/timeout/__init__.py
rsstt/helpers/timeout/_helper.py
rsstt/i18n/__init__.py
rsstt/i18n/ar.json
rsstt/i18n/be.json
rsstt/i18n/ca.json
rsstt/i18n/cs.json
rsstt/i18n/de.json
rsstt-2.10.0.dist-info/licenses/LICENSE
rsstt-2.10.0.dist-info/METADATA
rsstt-2.10.0.dist-info/WHEEL
rsstt-2.10.0.dist-info/top_level.txt
rsstt-2.10.0.dist-info/RECORD
