Metadata-Version: 2.4
Name: rsstt
Version: 2.10.0
Summary: A Telegram RSS bot that cares about your reading experience
Home-page: https://github.com/Rongronggg9/RSS-to-Telegram-Bot
Author: Rongrong
Author-email: i@rong.moe
License: OSI Approved :: GNU Affero General Public License v3 or later (AGPLv3+)
Project-URL: Bug Tracker, https://github.com/Rongronggg9/RSS-to-Telegram-Bot/issues
Project-URL: Documentation, https://github.com/Rongronggg9/RSS-to-Telegram-Bot/blob/dev/docs/README.md
Project-URL: Source Code, https://github.com/Rongronggg9/RSS-to-Telegram-Bot
Project-URL: Changelog, https://github.com/Rongronggg9/RSS-to-Telegram-Bot/blob/dev/docs/CHANGELOG.md
Platform: Linux
Platform: Windows
Platform: MacOS
Classifier: Development Status :: 5 - Production/Stable
Classifier: Environment :: Console
Classifier: Framework :: AsyncIO
Classifier: Framework :: aiohttp
Classifier: License :: OSI Approved :: GNU Affero General Public License v3 or later (AGPLv3+)
Classifier: Operating System :: POSIX :: Linux
Classifier: Operating System :: Microsoft :: Windows
Classifier: Operating System :: MacOS
Classifier: Programming Language :: Python :: 3 :: Only
Classifier: Programming Language :: Python :: 3.9
Classifier: Programming Language :: Python :: 3.10
Classifier: Programming Language :: Python :: 3.11
Classifier: Programming Language :: Python :: 3.12
Classifier: Programming Language :: Python :: Implementation :: CPython
Classifier: Topic :: Communications :: Chat
Classifier: Topic :: Internet
Classifier: Topic :: Multimedia
Requires-Python: >=3.9
License-File: LICENSE
Requires-Dist: cryptg==0.5.0.post0
Requires-Dist: telethon==1.39.0
Requires-Dist: aiographfix==0.2.2
Requires-Dist: feedparser==6.0.11
Requires-Dist: listparser[lxml]==0.20
Requires-Dist: pillow==11.1.0
Requires-Dist: beautifulsoup4==4.12.3
Requires-Dist: lxml==5.3.1
Requires-Dist: rapidfuzz==3.12.2
Requires-Dist: emoji==2.14.1
Requires-Dist: minify-html==0.15.0
Requires-Dist: minify-html-onepass==0.15.0
Requires-Dist: matplotlib==3.9.4
Requires-Dist: asyncpg==0.30.0
Requires-Dist: tortoise-orm[accel]==0.24.2
Requires-Dist: aerich==0.8.1
Requires-Dist: aiohttp[speedups]==3.11.14
Requires-Dist: aiohttp-socks==0.10.1
Requires-Dist: aiohttp-retry==2.9.1
Requires-Dist: python-socks[asyncio]==2.7.1
Requires-Dist: dnspython[idna]==2.7.0
Requires-Dist: yarl==1.18.3
Requires-Dist: propcache==0.3.0
Requires-Dist: colorlog==6.9.0
Requires-Dist: APScheduler==3.11.0
Requires-Dist: python-dotenv==1.0.1
Requires-Dist: multidict==6.2.0
Requires-Dist: asyncstdlib==3.13.1
Requires-Dist: cachetools==5.5.2
Requires-Dist: CJKwrap==2.2
Requires-Dist: typing-extensions==4.12.2
Requires-Dist: uvloop==0.21.0; sys_platform != "win32" and sys_platform != "cygwin" and sys_platform != "cli"
Requires-Dist: isal==1.7.2; platform_machine == "x86_64" or platform_machine == "AMD64" or platform_machine == "aarch64"
Dynamic: license-file
Dynamic: requires-dist
